{"id": "9557587f-7ad4-4725-a92c-6765700c0719", "code": "from dataclasses import dataclass\n\n@dataclass\nclass Triple:\n    subject: str\n    predicate: str\n    object: str\n\n# EVOLVE-BLOCK-START\n\ndef predict(triples: list[Triple]) -> str:\n    \"\"\"\n    Convert a list of triples about an astronaut (or related entities) into a single,\n    fluent English sentence. Handles common astronaut predicates with custom phrasing\n    and falls back to a generic pattern for unknown predicates.\n    \"\"\"\n    if not triples:\n        return \"\"\n\n    clauses: list[str] = []\n    for t in triples:\n        s, p, o = t.subject, t.predicate, t.object\n\n        # Custom phrasing for known predicates\n        if p == \"birthDate\":\n            clauses.append(f\"{s} was born on {o}\")\n        elif p == \"deathDate\":\n            clauses.append(f\"{s} died on {o}\")\n        elif p == \"birthPlace\":\n            clauses.append(f\"{s} was born in {o}\")\n        elif p == \"deathPlace\":\n            clauses.append(f\"{s} died in {o}\")\n        elif p == \"nationality\":\n            clauses.append(f\"{s} is a {o} astronaut\")\n        elif p == \"occupation\":\n            clauses.append(f\"{s} worked as a {o}\")\n        elif p == \"status\":\n            clauses.append(f\"{s} is {o.lower()}\")\n        elif p == \"mission\":\n            clauses.append(f\"{s} participated in the {o} mission\")\n        elif p == \"timeInSpace\":\n            clauses.append(f\"{s} spent {o} minutes in space\")\n        elif p == \"selectedByNasa\":\n            clauses.append(f\"{s} was selected by NASA in {o}\")\n        elif p == \"dateOfRetirement\":\n            clauses.append(f\"{s} retired in {o}\")\n        elif p == \"title\":\n            clauses.append(f\"{s} held the title of {o}\")\n        elif p == \"ribbonAward\":\n            clauses.append(f\"{s} received the {o}\")\n        elif p == \"awards\":\n            clauses.append(f\"{s} received {o} awards\")\n        elif p == \"award\":\n            clauses.append(f\"{s} was awarded the {o}\")\n        elif p == \"commander\":\n            clauses.append(f\"The commander of {s} was {o}\")\n        elif p == \"backupPilot\":\n            clauses.append(f\"The backup pilot of {s} was {o}\")\n        elif p == \"crewMembers\":\n            clauses.append(f\"The crew members of {s} include {o}\")\n        elif p == \"operator\":\n            clauses.append(f\"{s} was operated by {o}\")\n        elif p == \"representative\":\n            clauses.append(f\"The representative of {s} is {o}\")\n        elif p == \"alternativeName\":\n            clauses.append(f\"{s} is also known as {o}\")\n        else:\n            # Generic fallback\n            clauses.append(f\"{s} {p} {o}\")\n\n    # Combine clauses into a single fluent sentence\n    if len(clauses) == 1:\n        sentence = clauses[0] + \".\"\n    else:\n        sentence = \", \".join(clauses[:-1]) + \", and \" + clauses[-1] + \".\"\n    return sentence\n\n# EVOLVE-BLOCK-END", "changes_description": null, "language": "python", "parent_id": "3d7f632e-de37-4d1c-b686-929eaa03069d", "generation": 1, "timestamp": 1774855981.280116, "iteration_found": 169, "metrics": {"combined_score": 0.0006683143845773603, "BLUE score": 0.3117165963545508}, "complexity": 0.0, "diversity": 0.0, "metadata": {"changes": "Change 1: Replace:\n  def predict(triples: list[Triple]) -> str:\n      return f\"The {triples[0].predicate} of {triples[0].subject} is {triples[0].object}.\"\nwith:\n  def predict(triples: list[Triple]) -> str:\n      \"\"\"\n      Convert a list of triples about an astronaut (or related entities) into a single,\n      fluent English sentence. Handles common astronaut predicates with custom phrasing\n      and falls back to a generic pattern for unknown predicates.\n      \"\"\"\n      if not triples:\n          return \"\"\n  \n      clauses: list[str] = []\n      for t in triples:\n          s, p, o = t.subject, t.predicate, t.object\n  \n          # Custom phrasing for known predicates\n          if p == \"birthDate\":\n              clauses.append(f\"{s} was born on {o}\")\n          elif p == \"deathDate\":\n              clauses.append(f\"{s} died on {o}\")\n          elif p == \"birthPlace\":\n              clauses.append(f\"{s} was born in {o}\")\n          elif p == \"deathPlace\":\n              clauses.append(f\"{s} died in {o}\")\n          elif p == \"nationality\":\n              clauses.append(f\"{s} is a {o} astronaut\")\n          elif p == \"occupation\":\n              clauses.append(f\"{s} worked as a {o}\")\n          elif p == \"status\":\n              clauses.append(f\"{s} is {o.lower()}\")\n          elif p == \"mission\":\n              clauses.append(f\"{s} participated in the {o} mission\")\n  ... (36 more lines)", "parent_metrics": {"error": 0.0, "timeout": true}, "island": 0}, "prompts": null, "artifacts_json": null, "artifact_dir": null, "embedding": null}