{"id": "b0f16102-6cd1-48b5-bf1f-20ec3195d9f0", "code": "from dataclasses import dataclass\n\n@dataclass\nclass Triple:\n    subject: str\n    predicate: str\n    object: str\n\n# EVOLVE-BLOCK-START\n\ndef predict(triples: list[Triple]) -> str:\n    sentence = \"\"\n    subject = \"\"\n    for triple in triples:\n        if not sentence:\n            subject = triple.subject\n            sentence += f\"{triple.subject} \"\n        if triple.predicate == \"country\":\n            sentence += f\"is in {triple.object} \"\n        elif triple.predicate == \"capital\":\n            sentence += f\"and its capital is {triple.object} \"\n        elif triple.predicate == \"areaTotal\":\n            sentence += f\"with a total area of {triple.object} \"\n        elif triple.predicate == \"populationTotal\":\n            sentence += f\"and has a population of {triple.object} \"\n        elif triple.predicate == \"areaOfWater\":\n            sentence += f\"with an area of water of {triple.object} \"\n        elif triple.predicate == \"areaOfLand\":\n            sentence += f\"and an area of land of {triple.object} \"\n        elif triple.predicate == \"elevationAboveTheSeaLevel\":\n            sentence += f\"at an elevation of {triple.object} \"\n        elif triple.predicate == \"isPartOf\":\n            if \"is part of\" in sentence:\n                sentence += f\" and also part of {triple.object} \"\n            else:\n                sentence += f\" is part of {triple.object} \"\n        elif triple.predicate == \"utcOffset\":\n            sentence += f\" is in the {triple.object} UTC offset \"\n        elif triple.predicate == \"populationDensity\":\n            sentence += f\"has a population density of {triple.object} \"\n        elif triple.predicate == \"areaCode\":\n            sentence += f\"has area codes {triple.object} \"\n        elif triple.predicate == \"leaderTitle\":\n            sentence += f\"has a {triple.object} \"\n        elif triple.predicate == \"leader\":\n            sentence += f\"is led by {triple.object} \"\n        elif triple.predicate == \"postalCode\":\n            sentence += f\"has postal codes {triple.object} \"\n        elif triple.predicate == \"largestCity\":\n            sentence += f\"largest city is {triple.object} \"\n        elif triple.predicate == \"language\":\n            sentence += f\"speaks {triple.object} \"\n        elif triple.predicate == \"location\":\n            sentence += f\"is located in {triple.object} \"\n        elif triple.predicate == \"chairperson\":\n            sentence += f\"chairperson is {triple.object} \"\n        elif triple.predicate == \"headquarter\":\n            sentence += f\"headquarter is {triple.object} \"\n        elif triple.predicate == \"countySeat\":\n            sentence += f\"county seat is {triple.object} \"\n        elif triple.predicate == \"demonym\":\n            sentence += f\"people are called {triple.object} \"\n        elif triple.predicate == \"ethnicGroup\":\n            sentence += f\"has an ethnic group of {triple.object} \"\n        elif triple.predicate == \"state\":\n            sentence += f\"is in the state of {triple.object} \"\n        elif triple.predicate == \"populationMetro\":\n            sentence += f\"has a metropolitan population of {triple.object} \"\n        elif triple.predicate == \"type\":\n            sentence += f\"is a {triple.object} \"\n        elif triple.predicate == \"governmentType\":\n            sentence += f\"has a {triple.object} government \"\n        elif triple.predicate == \"timeZone\":\n            sentence += f\"is in the {triple.object} time zone \"\n        else:\n            sentence += f\"and {triple.predicate} is {triple.object} \"\n\n    return sentence.strip()\n\n# EVOLVE-BLOCK-END", "language": "python", "parent_id": "cf674392-ac3e-4c99-9c7f-043c3a223582", "generation": 2, "timestamp": 1769080739.082029, "iteration_found": 269, "metrics": {"combined_score": 0.3564434391056395}, "complexity": 0.0, "diversity": 0.0, "metadata": {"changes": "Change 1: Replace 4 lines with 7 lines", "parent_metrics": {"combined_score": 0.3658782068718178}, "island": 1}, "prompts": {"diff_user": {"system": "You are an expert in fixing your collegues code. You know that the code should be in format:\n<<<<<<< SEARCH\n# Original code to find and replace (must match exactly, indentations and endlines as well)\n=======\n# New replacement code\n>>>>>>> REPLACE\nProvided the incorrect format of SEARCH/REPLACE fix it to a correct format.\n        ", "user": "An incorrect diff format was detected in this change:\nHere's an improvement focusing on more natural sentence flow and handling multiple 'isPartOf' relationships:\n\n```diff\n<<<<<<< SEARCH\n        elif triple.predicate == \"isPartOf\":\n            sentence += f\"is part of {triple.object} \"\n        elif triple.predicate == \"utcOffset\":\n            sentence += f\"has a UTC offset of {triple.object} \"\n>>>>>>> REPLACE\n        elif triple.predicate == \"isPartOf\":\n            if \"is part of\" in sentence:\n                sentence += f\" and also part of {triple.object} \"\n            else:\n                sentence += f\" is part of {triple.object} \"\n        elif triple.predicate == \"utcOffset\":\n            sentence += f\" is in the {triple.object} UTC offset \"\n```\nPlease fix it to the correct format.", "responses": ["```\n<<<<<<< SEARCH\n        elif triple.predicate == \"isPartOf\":\n            sentence += f\"is part of {triple.object} \"\n        elif triple.predicate == \"utcOffset\":\n            sentence += f\"has a UTC offset of {triple.object} \"\n=======\n        elif triple.predicate == \"isPartOf\":\n            if \"is part of\" in sentence:\n                sentence += f\" and also part of {triple.object} \"\n            else:\n                sentence += f\" is part of {triple.object} \"\n        elif triple.predicate == \"utcOffset\":\n            sentence += f\" is in the {triple.object} UTC offset \"\n>>>>>>> REPLACE\n```"]}}, "artifacts_json": "{\"poor_program_score_7\": \"The program did very poorly with BLEU score 0.0. The input triples were:\\nAlbany, Oregon | elevationAboveTheSeaLevel | 64.008\\nThe generated text was:\\nAlbany, Oregon at an elevation of 64.008\\nThe example correct sentences are:\\nAlbany, Oregon is 64,008 above sea level.\\nAlbany, Oregon is located at 64.008 above sea level.\\n\", \"poor_program_score_69\": \"The program did very poorly with BLEU score 0.0. The input triples were:\\nAlexandria, Indiana | isPartOf | Indiana\\nIndiana | country | United States\\nThe generated text was:\\nAlexandria, Indiana  is part of Indiana is in United States\\nThe example correct sentences are:\\nAlexandria is part of the state of Indiana, which can be found in the United States.\\nAlexandria can be found in the state of Indiana in the United States.\\nAlexandria is located in Indiana, United States.\\n\", \"poor_program_score_139\": \"The program did very poorly with BLEU score 0.0. The input triples were:\\nCalifornia | country | United States\\nThe generated text was:\\nCalifornia is in United States\\nThe example correct sentences are:\\nCalifornia is in the United States.\\nCalifornia is in the U.S.\\n\", \"poor_program_score_140\": \"The program did very poorly with BLEU score 0.0. The input triples were:\\nIndiana | capital | Indianapolis\\nThe generated text was:\\nIndiana and its capital is Indianapolis\\nThe example correct sentences are:\\nIndianapolis is the capital of Indiana.\\n\", \"poor_program_score_22\": \"The program did very poorly with BLEU score 0.0. The input triples were:\\nAngola, Indiana | isPartOf | Indiana\\nThe generated text was:\\nAngola, Indiana  is part of Indiana\\nThe example correct sentences are:\\nAngola is a city in Indiana.\\nAngola is part of the state of Indiana.\\n\", \"poor_program_score_131\": \"The program did very poorly with BLEU score 0.0. The input triples were:\\nUnited States | ethnicGroup | Asian Americans\\nUnited States | language | English language\\nAlbany, Oregon | isPartOf | Oregon\\nOregon | capital | Salem, Oregon\\nAlbany, Oregon | country | United States\\nThe generated text was:\\nUnited States has an ethnic group of Asian Americans speaks English language  is part of Oregon and its capital is Salem, Oregon is in United States\\nThe example correct sentences are:\\nAlbany is a city in Oregon in the U.S. Salem is its capital. English is spoken in the U.S. and an ethnic group there are Asian Americans.\\nThe United States, where English is the spoken language, includes the Asian Americans among its ethnic groups. The country is the location of Albany, a city in Oregon which has the capital of Salem.\\n\", \"poor_program_score_26\": \"The program did very poorly with BLEU score 0.0. The input triples were:\\nArlington, Texas | areaOfWater | 82.8 (square kilometres)\\nThe generated text was:\\nArlington, Texas with an area of water of 82.8 (square kilometres)\\nThe example correct sentences are:\\nArlington, Texas has a water area of 82.8 square kilometres.\\nThe area of water within Arlington Texas is 82.8 sq km.\\n\", \"poor_program_score_51\": \"The program did very poorly with BLEU score 0.0. The input triples were:\\nOregon | capital | Salem, Oregon\\nThe generated text was:\\nOregon and its capital is Salem, Oregon\\nThe example correct sentences are:\\nSalem is the capital of Oregon.\\n\", \"poor_program_score_21\": \"The program did very poorly with BLEU score 0.0. The input triples were:\\nAnderson, Indiana | areaTotal | 107.43 (square kilometres)\\nThe generated text was:\\nAnderson, Indiana with a total area of 107.43 (square kilometres)\\nThe example correct sentences are:\\nAnderson, Indiana has an area of 107.43 square kilometres.\\nAnderson is located in Indiana, whose total area is 107.43 square kilometres.\\nThe total area of Anderson, Indiana is 107.43 square kilometres.\\n\", \"poor_program_score_98\": \"The program did very poorly with BLEU score 0.0. The input triples were:\\nAlbany, Oregon | isPartOf | Oregon\\nOregon | capital | Salem, Oregon\\nAlbany, Oregon | country | United States\\nThe generated text was:\\nAlbany, Oregon  is part of Oregon and its capital is Salem, Oregon is in United States\\nThe example correct sentences are:\\nAlbany is a city in Oregon, where the capital is Salem. Oregon is in the United States.\\nSalem is the capital of the state of Oregon (United States), where Albany is also located.\\nAlbany in the United States is located in Oregon where the capital is Salem.\\n\", \"poor_program_score_80\": \"The program did very poorly with BLEU score 0.0. The input triples were:\\nUnited States | ethnicGroup | African Americans\\nAngola, Indiana | isPartOf | United States\\nThe generated text was:\\nUnited States has an ethnic group of African Americans  is part of United States\\nThe example correct sentences are:\\nAngola, Indiana is part of the United States, where African Americans are an ethnic group.\\nAngola, Indiana is in the United States, where African Americans are an ethnic group.\\nAfrican Americans are an ethnic group within the United States where Angola, Indiana is located.\\n\", \"poor_program_score_114\": \"The program did very poorly with BLEU score 0.0. The input triples were:\\nAlbany, Georgia | isPartOf | Georgia (U.S. state)\\nUnited States | language | English language\\nAlbany, Georgia | country | United States\\nUnited States | ethnicGroup | African Americans\\nThe generated text was:\\nAlbany, Georgia  is part of Georgia (U.S. state) speaks English language is in United States has an ethnic group of African Americans\\nThe example correct sentences are:\\nAlbany is located in the US state of Georgia where English is the spoken language. African Americans are an ethnic group in the United States.\\nAlbany is part of the state of Georgia in the United States. The US is home to African Americans and English is the language spoken there.\\n\", \"poor_program_score_99\": \"The program did very poorly with BLEU score 0.0. The input triples were:\\nAlexandria, Indiana | isPartOf | Indiana\\nIndiana | capital | Indianapolis\\nIndiana | country | United States\\nThe generated text was:\\nAlexandria, Indiana  is part of Indiana and its capital is Indianapolis is in United States\\nThe example correct sentences are:\\nAlexandria is in Indiana in the United States and whose capital is Indianapolis.\\nAlexandria is located in Indiana (United States), the capital of that state is Indianapolis.\\nThe city of Alexandria is in Indiana U.S. and the state capital is Indianapolis.\\n\", \"poor_program_score_50\": \"The program did very poorly with BLEU score 0.0. The input triples were:\\nNew Mexico Senate | leader | John S\\u00e1nchez\\nThe generated text was:\\nNew Mexico Senate is led by John S\\u00e1nchez\\nThe example correct sentences are:\\nJohn S\\u00e1nchez, is one of the leaders, in the New Mexico Senate.\\nJohn Sanchez is the Senate leader of New Mexico.\\n\", \"poor_program_score_126\": \"The program did very poorly with BLEU score 0.0. The input triples were:\\nUnited States | demonym | Americans\\nAlbany, Oregon | isPartOf | Oregon\\nOregon | capital | Salem, Oregon\\nAlbany, Oregon | country | United States\\nUnited States | ethnicGroup | African Americans\\nThe generated text was:\\nUnited States people are called Americans  is part of Oregon and its capital is Salem, Oregon is in United States has an ethnic group of African Americans\\nThe example correct sentences are:\\nSalem is the capital of Oregon, the state where Albany is located, in the United States. The country where Americans live and where African Americans are one of the ethnic groups.\\nAlbany is a city in Oregon, the capital of which is Salem. Albany, Oregon is located within the United States, where the inhabitants are called Americans, and where African Americans are one of the ethnic groups.\\n\", \"poor_program_score_164\": \"The program did very poorly with BLEU score 0.0. The input triples were:\\nCiudad Ayala | utcOffset | \\u22126\\nCiudad Ayala | country | Mexico\\nThe generated text was:\\nCiudad Ayala  is in the \\u22126 UTC offset is in Mexico\\nThe example correct sentences are:\\nCiudad Ayala UTC offset is -6 in the country of Mexico.\\nCiudad Ayala has a UTC offset of -6 and is a city in Mexico.\\nCiudad Ayala falls into UTC offset -6 timezone and is located in the country of Mexico.\\n\", \"poor_program_score_27\": \"The program did very poorly with BLEU score 0.0. The input triples were:\\nArlington, Texas | areaTotal | 258.2 (square kilometres)\\nThe generated text was:\\nArlington, Texas with a total area of 258.2 (square kilometres)\\nThe example correct sentences are:\\nThe total area of Arlington (Texas) is 258.2 square kilometres.\\nArlington Texas has an area of 258.2 SqK.\\nThe total area of Arlington in Texas is 258.2 square kilometres.\\n\", \"poor_program_score_154\": \"The program did very poorly with BLEU score 0.0. The input triples were:\\nCiudad Ayala | leaderTitle | \\\"City Manager\\\"\\nCiudad Ayala | isPartOf | Morelos\\nMorelos | isPartOf | Cuernavaca\\nThe generated text was:\\nCiudad Ayala has a \\\"City Manager\\\"  is part of Morelos  and also part of Cuernavaca\\nThe example correct sentences are:\\nCuernavaca and Ciudad Ayala are parts of Morelos. One of the leaders of Ciudad Ayala is the City Manager.\\nBoth Ciudad Ayala and Cuernavacas are part of Morelos, and one of the leaders of Ciudad Ayala is the City Manager.\\nThe leader tittle for Ciudad Ayala is the city manager. Ciudad Ayala and Cuernavaca are part of Morelos.\\n\", \"poor_program_score_81\": \"The program did very poorly with BLEU score 0.0. The input triples were:\\nUnited States | ethnicGroup | Asian Americans\\nAlbany, Georgia | country | United States\\nThe generated text was:\\nUnited States has an ethnic group of Asian Americans is in United States\\nThe example correct sentences are:\\nAlbany is in Georgia in the United States where Asian Americans are an ethnic group.\\nThe United States includes the Asian Americans among its ethnic groups and is the location of Albany, Georgia.\\n\", \"poor_program_score_1\": \"The program did very poorly with BLEU score 0.0. The input triples were:\\nAkron, Ohio | areaCode | 234, 330\\nThe generated text was:\\nAkron, Ohio has area codes 234, 330\\nThe example correct sentences are:\\nThe area codes in Akron, Ohio are 234 and 330.\\n\", \"poor_program_score_66\": \"The program did very poorly with BLEU score 0.0. The input triples were:\\nWashington (state) | country | United States\\nThe generated text was:\\nWashington (state) is in United States\\nThe example correct sentences are:\\nWashington state is located within the United States.\\nWashington is a state is United States.\\n\", \"poor_program_score_107\": \"The program did very poorly with BLEU score 0.0. The input triples were:\\nUnited States | ethnicGroup | African Americans\\nUnited States | leader | Barack Obama\\nAlbuquerque, New Mexico | country | United States\\nThe generated text was:\\nUnited States has an ethnic group of African Americans is led by Barack Obama is in United States\\nThe example correct sentences are:\\nBarack Obama is the leader of the United States where Albuquerque, New Mexico is located and African Americans are one of the ethnic groups of the country.\\nAlbuquerque, New Mexico is located in the United States where Barack Obama is the president and African Americans are an ethnic group within the country.\\nAlbuquerque, New Mexico, is in the United States, where Barack Obama is a leader, and where African Americans are an ethnic group.\\n\", \"poor_program_score_143\": \"The program did very poorly with BLEU score 0.0. The input triples were:\\nAlbany, Oregon | isPartOf | Oregon\\nOregon | largestCity | Portland, Oregon\\nThe generated text was:\\nAlbany, Oregon  is part of Oregon largest city is Portland, Oregon\\nThe example correct sentences are:\\nPortland is the largest city in Oregon which also includes Albany.\\nPortland is the largest city in Oregon, the state which is home to Albany.\\nAlbany is a city in Oregon along with Portland which is the largest.\\n\", \"poor_program_score_44\": \"The program did very poorly with BLEU score 0.0. The input triples were:\\nMichigan | capital | Lansing, Michigan\\nThe generated text was:\\nMichigan and its capital is Lansing, Michigan\\nThe example correct sentences are:\\nLansing is the capital of Michigan.\\nThe capital of Michigan is Lansing.\\n\", \"poor_program_score_119\": \"The program did very poorly with BLEU score 0.0. The input triples were:\\nUnited States | ethnicGroup | African Americans\\nAlbuquerque, New Mexico | leaderTitle | New Mexico Senate\\nUnited States | leader | Barack Obama\\nAlbuquerque, New Mexico | country | United States\\nThe generated text was:\\nUnited States has an ethnic group of African Americans has a New Mexico Senate is led by Barack Obama is in United States\\nThe example correct sentences are:\\nLed by the New Mexico Senate, Albuquerque, New Mexico, is in the United States. The country where Barack Obama is the leader and African Americans are one of the ethnic groups.\\nThe New Mexico Senate leads Albuquerque in New Mexico, United States. Barack Obama is the leader of the United States, some other black people live there too.\\nAlbuquerque, New Mexico, United States, is led by the New Mexico Senate. Barack Obama is a leader of the United States, where African Americans constitute one of the ethnic groups.\\n\", \"poor_program_score_121\": \"The program did very poorly with BLEU score 0.0. The input triples were:\\nUnited States | ethnicGroup | African Americans\\nUnited States | language | English language\\nAngola, Indiana | isPartOf | Indiana\\nAngola, Indiana | country | United States\\nThe generated text was:\\nUnited States has an ethnic group of African Americans speaks English language  is part of Indiana is in United States\\nThe example correct sentences are:\\nAngola, a city in Indiana, is in the United States. The same English speaking country, where African Americans are one of the ethnic groups.\\nAngola, Indiana is in the United States, a country whose language is English. One of the ethnic groups within the U.S. are African Americans.\\nAngola, part of the state of Indiana, is in the United States. English is the language spoken in the U.S., and African Americans are one of the ethnic groups.\\n\", \"poor_program_score_42\": \"The program did very poorly with BLEU score 0.0. The input triples were:\\nIndiana | country | United States\\nThe generated text was:\\nIndiana is in United States\\nThe example correct sentences are:\\nIndiana is the United States.\\nIndiana is in the U.S.\\nIndiana is located within the United States.\\n\", \"poor_program_score_67\": \"The program did very poorly with BLEU score 0.0. The input triples were:\\nWashington (state) | largestCity | Seattle\\nThe generated text was:\\nWashington (state) largest city is Seattle\\nThe example correct sentences are:\\nSeattle is the largest city in Washington State.\\nThe largest city of Washington state is Seattle.\\n\", \"poor_program_score_32\": \"The program did very poorly with BLEU score 0.0. The input triples were:\\nAuburn, Alabama | elevationAboveTheSeaLevel | 214.0\\nThe generated text was:\\nAuburn, Alabama at an elevation of 214.0\\nThe example correct sentences are:\\nAuburn Alabama has an elevation above sea level of 214.\\nAuburn, Alabama is located at 214.0 above sea level.\\n\", \"poor_program_score_82\": \"The program did very poorly with BLEU score 0.0. The input triples were:\\nUnited States | ethnicGroup | Asian Americans\\nAlbany, Georgia | isPartOf | United States\\nThe generated text was:\\nUnited States has an ethnic group of Asian Americans  is part of United States\\nThe example correct sentences are:\\nAlbany, Georgia is part of the United States of American where Asian Americans are one of the ethnic groups.\\nAlbany, Georgia is in the United States, a country where one of the ethnic groups are Asian Americans.\\nThe Asian Americans are an ethnic group in the United States, where Albany, Georgia can be found.\\n\", \"poor_program_score_122\": \"The program did very poorly with BLEU score 0.0. The input triples were:\\nUnited States | ethnicGroup | African Americans\\nUnited States | leader | Barack Obama\\nAlbuquerque, New Mexico | leaderTitle | Mayor of Albuquerque\\nAlbuquerque, New Mexico | country | United States\\nThe generated text was:\\nUnited States has an ethnic group of African Americans is led by Barack Obama has a Mayor of Albuquerque is in United States\\nThe example correct sentences are:\\nAlbuquerque, New Mexico is located in the United States and led by the Mayor of Albuquerque. Barack Obama is the leader of the United States and African Americans are one of the ethnic groups in the country.\\nAlbuquerque in New Mexico, United States, is led by the Mayor of Albuquerque. Barack Obama is the leader of the United States and some other African Americans live there too.\\nThe leader of the United States was Barack Obama. The leader of Albuquerque, New Mexico, which is located in the United States, is the Mayor. African Americans are among the ethnic groups in the U.S.\\n\", \"poor_program_score_54\": \"The program did very poorly with BLEU score 0.0. The input triples were:\\nRandall County, Texas | countySeat | Canyon, Texas\\nThe generated text was:\\nRandall County, Texas county seat is Canyon, Texas\\nThe example correct sentences are:\\nCanyon, is the county seat of Randall County, which is in Texas.\\nRandall County is a county located in Texas with the county seat being Canyon.\\n\", \"poor_program_score_53\": \"The program did very poorly with BLEU score 0.0. The input triples were:\\nRandall County, Texas | country | United States\\nThe generated text was:\\nRandall County, Texas is in United States\\nThe example correct sentences are:\\nRandall County is in Texas, in the United States.\\nRandall County is located in Texas, United States.\\nRandall County in Texas is located within the United States.\\n\", \"poor_program_score_39\": \"The program did very poorly with BLEU score 0.0. The input triples were:\\nCalifornia | language | Chinese language\\nThe generated text was:\\nCalifornia speaks Chinese language\\nThe example correct sentences are:\\nChinese is one of the languages spoken in California.\\nSome parts of California speak Chinese.\\nThe Chinese language is spoken in California.\\n\", \"poor_program_score_104\": \"The program did very poorly with BLEU score 0.0. The input triples were:\\nAuburn, Washington | isPartOf | Pierce County, Washington\\nAuburn, Washington | country | United States\\nAuburn, Washington | isPartOf | King County, Washington\\nThe generated text was:\\nAuburn, Washington  is part of Pierce County, Washington is in United States  and also part of King County, Washington\\nThe example correct sentences are:\\nAuburn is in Pierce County and Kings County, Washington, US.\\nAuburn is part of both Pierce County and King County in Washington, United States.\\nAuburn is part of both Pierce county and King county, in Washington, in the United States.\\n\", \"poor_program_score_93\": \"The program did very poorly with BLEU score 0.0. The input triples were:\\nUnited States | leader | Barack Obama\\nAlbuquerque, New Mexico | country | United States\\nThe generated text was:\\nUnited States is led by Barack Obama is in United States\\nThe example correct sentences are:\\nAlbuquerque, New Mexico, is located in the United States, where Barack Obama is leader.\\nThe leader of the United States, where Albuquerque, New Mexico is located is Barack Obama.\\nBarack Obama is a leader of the United States where Albuquerque, New Mexico is located.\\n\", \"poor_program_score_159\": \"The program did very poorly with BLEU score 0.0. The input triples were:\\nCiudad Ayala | populationMetro | 1777539\\nCiudad Ayala | leaderTitle | \\\"City Manager\\\"\\nCiudad Ayala | type | City\\nCiudad Ayala | governmentType | Council-manager government\\nThe generated text was:\\nCiudad Ayala has a metropolitan population of 1777539 has a \\\"City Manager\\\" is a City has a Council-manager government government\\nThe example correct sentences are:\\nCiudad Ayala is a city with a metropolitan area of 1,777,539 which uses a council-manager type government employing a City Manager as one of the leaders.\\nCiudad Ayala city had City manager as one of the leaders, has council-manager government with population of 1,777,539.\\nCiudad Ayala is a city, whose government type is council manager, and the city leader title is city manager. Its population in the metropolitan area is 1777539.\\n\", \"poor_program_score_138\": \"The program did very poorly with BLEU score 0.0. The input triples were:\\nArlington, Texas | elevationAboveTheSeaLevel | 184.0\\nThe generated text was:\\nArlington, Texas at an elevation of 184.0\\nThe example correct sentences are:\\nArlington Texas is has an elevation of 184 above sea level.\\nArlington in Texas is located at 184.0 above sea level.\\n\", \"poor_program_score_25\": \"The program did very poorly with BLEU score 0.0. The input triples were:\\nAntioch, California | populationTotal | 102372\\nThe generated text was:\\nAntioch, California and has a population of 102372\\nThe example correct sentences are:\\nThe population of Antioch California is 102372.\\nThe total population of Antioch, California is 102372.\\nThe population of Antioch, California is 102372.\\n\", \"poor_program_score_40\": \"The program did very poorly with BLEU score 0.0. The input triples were:\\nCalifornia | language | English language\\nThe generated text was:\\nCalifornia speaks English language\\nThe example correct sentences are:\\nThe English language is spoken in California.\\nEnglish is spoken in California.\\n\", \"poor_program_score_11\": \"The program did very poorly with BLEU score 0.0. The input triples were:\\nAmarillo, Texas | areaCode | 806\\nThe generated text was:\\nAmarillo, Texas has area codes 806\\nThe example correct sentences are:\\nThe area code for Amarillo, Texas is 806.\\n806 is the area code for Amarillo, Texas.\\n\", \"poor_program_score_141\": \"The program did very poorly with BLEU score 0.0. The input triples were:\\nNew Jersey | capital | Trenton, New Jersey\\nThe generated text was:\\nNew Jersey and its capital is Trenton, New Jersey\\nThe example correct sentences are:\\nTrenton is the capital of New Jersey.\\nThe capital of the state of New Jersey is Trenton.\\n\", \"poor_program_score_52\": \"The program did very poorly with BLEU score 0.0. The input triples were:\\nPierce County, Washington | largestCity | Tacoma, Washington\\nThe generated text was:\\nPierce County, Washington largest city is Tacoma, Washington\\nThe example correct sentences are:\\nPierce County is the largest city in Tacoma, Washington.\\nTacoma, Washington, is the largest city in Pierce County.\\n\", \"poor_program_score_68\": \"The program did very poorly with BLEU score 0.0. The input triples were:\\nAlbany, Georgia | isPartOf | Georgia (U.S. state)\\nGeorgia (U.S. state) | capital | Atlanta\\nThe generated text was:\\nAlbany, Georgia  is part of Georgia (U.S. state) and its capital is Atlanta\\nThe example correct sentences are:\\nAlbany is located in the US state of Georgia, of which Atlanta is the capital.\\n\", \"poor_program_score_36\": \"The program did very poorly with BLEU score 0.0. The input triples were:\\nAustin, Texas | areaOfLand | 686.0 (square kilometres)\\nThe generated text was:\\nAustin, Texas and an area of land of 686.0 (square kilometres)\\nThe example correct sentences are:\\nAustin, Texas has a land area of 686 square kilometres.\\nAustin, Texas has a area of land that measures 686.0 (square kilometers).\\nAustin, Texas covers 686.0 square kilometres of land.\\n\", \"poor_program_score_37\": \"The program did very poorly with BLEU score 0.0. The input triples were:\\nAustin, Texas | leaderTitle | City Manager\\nThe generated text was:\\nAustin, Texas has a City Manager\\nThe example correct sentences are:\\nThe city manager is the leader of Austin, Texas.\\nThe City Manager leads Austin, Texas.\\n\", \"poor_program_score_133\": \"The program did very poorly with BLEU score 0.0. The input triples were:\\nUnited States | language | English language\\nAlbany, Oregon | isPartOf | Oregon\\nOregon | capital | Salem, Oregon\\nAlbany, Oregon | country | United States\\nUnited States | ethnicGroup | African Americans\\nThe generated text was:\\nUnited States speaks English language  is part of Oregon and its capital is Salem, Oregon is in United States has an ethnic group of African Americans\\nThe example correct sentences are:\\nEnglish is the language spoken in the United States which includes the African Americans among its ethnic groups. The country is the location of Albany in the state of Oregon where the capital is Salem.\\n\", \"poor_program_score_73\": \"The program did very poorly with BLEU score 0.0. The input triples were:\\nAtlanta | country | United States\\nUnited States | ethnicGroup | Asian Americans\\nThe generated text was:\\nAtlanta is in United States has an ethnic group of Asian Americans\\nThe example correct sentences are:\\nOne of the ethnic groups in the United States (where Atlanta is located) is Asian Americans.\\nAtlanta is in the United States, where one of the ethnic groups, is Asian Americans.\\nAtlanta is in the United States, the country where Asian Americans are an ethnic group.\\n\", \"poor_program_score_46\": \"The program did very poorly with BLEU score 0.0. The input triples were:\\nMichigan | language | English language\\nThe generated text was:\\nMichigan speaks English language\\nThe example correct sentences are:\\nThe English language is spoken in Michigan.\\nEnglish is the language spoken in Michigan.\\n\", \"poor_program_score_163\": \"The program did very poorly with BLEU score 0.0. The input triples were:\\nCiudad Ayala | leaderTitle | \\\"City Manager\\\"\\nCiudad Ayala | type | City\\nCiudad Ayala | governmentType | Council-manager government\\nCiudad Ayala | utcOffset | \\u22126\\nThe generated text was:\\nCiudad Ayala has a \\\"City Manager\\\" is a City has a Council-manager government government  is in the \\u22126 UTC offset\\nThe example correct sentences are:\\nLed by the City Manager, the city of Ciudad Ayala falls into UTC offset -6 time zone. It utilises a type of government known as council-manager government.\\nThe city of Ciudad Ayala is overseen by the city manager. Its UTC offset is -6 and its government type is council manager.\\nCiudad Ayala is a city with a UTC offset of -6. The government type in the city of Ciudad Ayala is council-manager and the leader title for Ciudad Ayala is City Manager.\\n\"}", "artifact_dir": null, "embedding": null}