{"id": "97b65b1e-8dd8-4f84-b043-e8828b98238a", "code": "from dataclasses import dataclass\n\n@dataclass\nclass Triple:\n    subject: str\n    predicate: str\n    object: str\n\n# EVOLVE-BLOCK-START\n\ndef predict(triples: list[Triple]) -> str:\n    \"\"\"\n    Convert a list of triples into a single fluent sentence.\n    Uses natural\u2011language templates for known predicates and falls back to a generic form.\n    All clauses are combined into one sentence.\n    \"\"\"\n    if not triples:\n        return \"\"\n\n    # Templates for predicates \u2013 {subj}, {obj} will be substituted\n    templates = {\n        \"country\": \"{subj} is based in {obj}\",\n        \"foundingDate\": \"{subj} was founded on {obj}\",\n        \"industry\": \"{subj} operates in the {obj} industry\",\n        \"city\": \"{subj} is located in {obj}\",\n        \"netIncome\": \"{subj} reported a net income of ${obj}\",\n        \"operatingIncome\": \"{subj} reported an operating income of ${obj}\",\n        \"regionServed\": \"{subj} serves the {obj} region\",\n        \"areaTotal\": \"{subj} covers a total area of {obj}\",\n        \"leader\": \"{subj} is led by {obj}\",\n        \"leaderTitle\": \"{obj} of {subj}\",\n        \"populationDensity\": \"{subj} has a population density of {obj} per km\u00b2\",\n        \"foundationPlace\": \"{subj} was founded in {obj}\",\n        \"numberOfEmployees\": \"{subj} employs {obj} people\",\n        \"numberOfLocations\": \"{subj} has {obj} locations\",\n        \"service\": \"{subj} provides {obj} services\",\n        \"type\": \"{subj} is a {obj}\",\n        \"alternativeName\": \"{subj} is also known as {obj}\",\n        \"birthDate\": \"{subj} was born on {obj}\",\n        \"keyPerson\": \"{subj} has key person {obj}\",\n        \"cost\": \"{subj} cost {obj}\",\n        \"location\": \"{subj} is located in {obj}\",\n        \"product\": \"{subj} produces {obj}\",\n        \"subsidiary\": \"{subj} has subsidiary {obj}\",\n        \"timeZone\": \"{subj} is in the {obj}\",\n        \"isPartOf\": \"{subj} is part of {obj}\",\n        \"parentCompany\": \"{subj} is owned by {obj}\",\n        \"capital\": \"{subj} has capital {obj}\",\n        \"motto\": \"{subj}'s motto is {obj}\",\n        \"officialLanguage\": \"{subj} official language is {obj}\",\n        \"leaderParty\": \"{subj} leader belongs to {obj}\",\n        \"areaUrban\": \"{subj} has an urban area of {obj}\",\n        \"part\": \"{subj} includes {obj}\",\n        \"revenue\": \"{subj} generated revenue of {obj}\",\n        \"ethnicGroup\": \"{subj} includes ethnic group {obj}\",\n        \"governmentType\": \"{subj} has a government type of {obj}\",\n        \"percentageOfAreaWater\": \"{subj} has {obj}% water area\",\n        \"longName\": \"{subj} is officially known as {obj}\",\n        \"populationTotal\": \"{subj} has a population of {obj}\",\n        \"language\": \"{subj} speaks {obj}\",\n        \"elevationAboveTheSeaLevel\": \"{subj} is at {obj} meters above sea level\",\n    }\n\n    def render(triple: Triple) -> str:\n        tmpl = templates.get(triple.predicate)\n        if tmpl:\n            # Simple placeholder substitution\n            return tmpl.format(subj=triple.subject, obj=triple.object)\n        # Fallback generic phrasing\n        return f\"{triple.subject} has {triple.predicate} {triple.object}\"\n\n    # Build clause for each triple preserving order\n    clauses = [render(t) for t in triples]\n\n    # Combine clauses into a single fluent sentence\n    if len(clauses) == 1:\n        sentence = clauses[0] + \".\"\n    else:\n        sentence = \", \".join(clauses[:-1]) + \", and \" + clauses[-1] + \".\"\n\n    return sentence\n\n# EVOLVE-BLOCK-END", "changes_description": null, "language": "python", "parent_id": "678c45c4-5858-46ad-8f5f-e70a38a455e0", "generation": 2, "timestamp": 1774847335.7087831, "iteration_found": 103, "metrics": {"combined_score": 0.0011318337572527534, "BLUE score": 0.3429141766260392}, "complexity": 0.0, "diversity": 0.0, "metadata": {"changes": "Change 1: Replace:\n  def predict(triples: list[Triple]) -> str:\n      \"\"\"\n      Convert a list of triples into a single fluent sentence.\n      Each triple is expressed as \u201c<subject> has <predicate> <object>\u201d.\n      Multiple triples are concatenated with commas and an 'and' before the last one.\n      \"\"\"\n      if not triples:\n          return \"\"\n  \n      # Build simple clause for each triple\n      clauses = [\n          f\"{t.subject} has {t.predicate} {t.object}\"\n          for t in triples\n      ]\n  \n      # Join clauses into a single sentence\n      if len(clauses) == 1:\n          sentence = clauses[0] + \".\"\n      else:\n          sentence = \", \".join(clauses[:-1]) + \", and \" + clauses[-1] + \".\"\n  \n      return sentence\nwith:\n  def predict(triples: list[Triple]) -> str:\n      \"\"\"\n      Convert a list of triples into a single fluent sentence.\n      Uses natural\u2011language templates for known predicates and falls back to a generic form.\n      All clauses are combined into one sentence.\n      \"\"\"\n      if not triples:\n          return \"\"\n  \n      # Templates for predicates \u2013 {subj}, {obj} will be substituted\n      templates = {\n          \"country\": \"{subj} is based in {obj}\",\n          \"foundingDate\": \"{subj} was founded on {obj}\",\n          \"industry\": \"{subj} operates in the {obj} industry\",\n          \"city\": \"{subj} is located in {obj}\",\n          \"netIncome\": \"{subj} reported a net income of ${obj}\",\n          \"operatingIncome\": \"{subj} reported an operating income of ${obj}\",\n          \"regionServed\": \"{subj} serves the {obj} region\",\n          \"areaTotal\": \"{subj} covers a total area of {obj}\",\n          \"leader\": \"{subj} is led by {obj}\",\n          \"leaderTitle\": \"{obj} of {subj}\",\n          \"populationDensity\": \"{subj} has a population density of {obj} per km\u00b2\",\n          \"foundationPlace\": \"{subj} was founded in {obj}\",\n          \"numberOfEmployees\": \"{subj} employs {obj} people\",\n          \"numberOfLocations\": \"{subj} has {obj} locations\",\n          \"service\": \"{subj} provides {obj} services\",\n          \"type\": \"{subj} is a {obj}\",\n          \"alternativeName\": \"{subj} is also known as {obj}\",\n          \"birthDate\": \"{subj} was born on {obj}\",\n          \"keyPerson\": \"{subj} has key person {obj}\",\n  ... (41 more lines)", "parent_metrics": {"combined_score": 0.0031343088662383945, "BLUE score": 0.1327119744689082}, "island": 0}, "prompts": null, "artifacts_json": null, "artifact_dir": null, "embedding": null}